setup.cfg
setup.py
pykurento/__init__.py
pykurento/client.py
pykurento/media.py
pykurento/transport.py
pykurento.egg-info/PKG-INFO
pykurento.egg-info/SOURCES.txt
pykurento.egg-info/dependency_links.txt
pykurento.egg-info/not-zip-safe
pykurento.egg-info/requires.txt
pykurento.egg-info/top_level.txt