Metadata-Version: 1.1
Name: pykurento
Version: 0.0.1
Summary: A python kurento client based on websocket-client
Home-page: https://github.com/minervaproject/pykurento
Author: Gene Hallman, MinervaProject
Author-email: gene@minervaproject.com
License: LGPL
Download-URL: https://github.com/minervaproject/pykurento/tarball/0.0.1
Platform: UNKNOWN
